allow_agent/__init__.py
allow_agent/init_models.py
allow_agent/safety.py
allow_agent/test_allowagent.py
allow_agent-1.1.0.dist-info/LICENSE
allow_agent-1.1.0.dist-info/METADATA
allow_agent-1.1.0.dist-info/WHEEL
allow_agent-1.1.0.dist-info/entry_points.txt
allow_agent-1.1.0.dist-info/top_level.txt
allow_agent-1.1.0.dist-info/RECORD
