Metadata-Version: 2.2
Name: allow-agent
Version: 1.1.0
Summary: A lightweight Python framework for agent content moderation.
Author: allow-agent
License: MIT
Project-URL: Homepage, https://github.com/EthicsGPT/allow-agent
Project-URL: Issues, https://github.com/EthicsGPT/allow-agent/issues
Keywords: agent,proxy,llm,prompt,agentic,ai,openai,log
Classifier: Programming Language :: Python :: 3
Classifier: License :: OSI Approved :: MIT License
Classifier: Operating System :: OS Independent
Requires-Python: >=3.7
License-File: LICENSE
Requires-Dist: spacy
Requires-Dist: en_core_web_lg
Requires-Dist: llm-guard
Requires-Dist: requests
Requires-Dist: aiohttp
Requires-Dist: httpx
Requires-Dist: urllib3
